{"data":[{"link":"https://seller.uzum.uz/seller/12269/products/all/id/658407/main","saled":1,"returnCount":0,"statusSKU":"Есть товары в продаже, находятся на складе","statusCard":"Можно редактировать","status":"В продаже","title":"Унисекс Очки солнцезащитные Трансформер 5в1 магнитные / 5 сменных линз / поляризационные","rating":0,"sku":"ОЧКИ7","id":658407},{"link":"https://seller.uzum.uz/seller/12269/products/all/id/628644/main","saled":0,"returnCount":0,"statusSKU":"Товар заблокирован","statusCard":"Можно редактировать","status":"Заблокирован","title":"Очки в металлической оправе с защитой от синего света/ Снижение напряжения глаз/ Blu-ray","rating":0,"sku":"ОЧКИ6","id":628644},{"link":"https://seller.uzum.uz/seller/12269/products/all/id/628599/main","saled":0,"returnCount":0,"statusSKU":"Товар заблокирован","statusCard":"Можно редактировать","status":"Заблокирован","title":"Очки для работы за компьютером с защитой от синего света/ Снижение напряжения глаз/ Легкие","rating":0,"sku":"ОЧКИ5","id":628599},{"link":"https://seller.uzum.uz/seller/12269/products/all/id/599622/main","saled":0,"returnCount":0,"statusSKU":"Товар заблокирован","statusCard":"Можно редактировать","status":"Заблокирован","title":"Очки для работы за компьютером с защитой от синего света/ Снижение напряжения глаз/ Легкие","rating":0,"sku":"ОЧКИ4","id":599622},{"link":"https://seller.uzum.uz/seller/12269/products/all/id/424532/main","saled":0,"returnCount":0,"statusSKU":"Есть товары в продаже, находятся на складе","statusCard":"Можно редактировать","status":"В продаже","title":"Женские очки для работы за компьютером с защитой от синего света 100%, Лёгкие и удобные","rating":0,"sku":"ОЧКИ3","id":424532},{"link":"https://seller.uzum.uz/seller/12269/products/all/id/424287/main","saled":0,"returnCount":0,"statusSKU":"Есть товары в продаже, находятся на складе","statusCard":"Можно редактировать","status":"В продаже","title":"Женские очки для работы за компьютером с защитой от синего света, Снижение напряжения глаз","rating":0,"sku":"ОЧКИ2","id":424287},{"link":"https://seller.uzum.uz/seller/12269/products/all/id/424126/main","saled":0,"returnCount":0,"statusSKU":"Создан акт к отправке","statusCard":"Можно редактировать","status":"Отправлен","title":"Женские защитные очки для компьютера с защитой UV-400 от синего света Anti Blue Light","rating":0,"sku":"ОЧКИ1","id":424126}]}